korotto/__init__.py
korotto-0.1.dist-info/LICENSE
korotto-0.1.dist-info/METADATA
korotto-0.1.dist-info/WHEEL
korotto-0.1.dist-info/top_level.txt
korotto-0.1.dist-info/RECORD
